{
  "root": [
    {
      "transcription": "CỘNGHOÀXÃ",
      "points": [
        [
          543,
          240
        ],
        [
          755,
          240
        ],
        [
          755,
          278
        ],
        [
          543,
          278
        ]
      ]
    },
    {
      "transcription": "HỘI",
      "points": [
        [
          743,
          247
        ],
        [
          814,
          247
        ],
        [
          814,
          271
        ],
        [
          743,
          271
        ]
      ]
    },
    {
      "transcription": "CHI",
      "points": [
        [
          809,
          245
        ],
        [
          864,
          245
        ],
        [
          864,
          271
        ],
        [
          809,
          271
        ]
      ]
    },
    {
      "transcription": "REP",
      "points": [
        [
          752,
          280
        ],
        [
          809,
          280
        ],
        [
          809,
          305
        ],
        [
          752,
          305
        ]
      ]
    },
    {
      "transcription": "JBLIC",
      "points": [
        [
          814,
          280
        ],
        [
          880,
          280
        ],
        [
          880,
          305
        ],
        [
          814,
          305
        ]
      ]
    },
    {
      "transcription": "OF",
      "points": [
        [
          893,
          280
        ],
        [
          932,
          280
        ],
        [
          932,
          307
        ],
        [
          893,
          307
        ]
      ]
    },
    {
      "transcription": "Độclp",
      "points": [
        [
          658,
          304
        ],
        [
          753,
          310
        ],
        [
          751,
          341
        ],
        [
          656,
          335
        ]
      ]
    },
    {
      "transcription": "-",
      "points": [
        [
          759,
          316
        ],
        [
          800,
          316
        ],
        [
          800,
          331
        ],
        [
          759,
          331
        ]
      ]
    },
    {
      "transcription": "Hạnh",
      "points": [
        [
          872,
          314
        ],
        [
          937,
          308
        ],
        [
          939,
          333
        ],
        [
          874,
          339
        ]
      ]
    },
    {
      "transcription": "Phú",
      "points": [
        [
          950,
          316
        ],
        [
          993,
          316
        ],
        [
          993,
          333
        ],
        [
          950,
          333
        ]
      ]
    },
    {
      "transcription": "Liberty",
      "points": [
        [
          812,
          347
        ],
        [
          896,
          349
        ],
        [
          895,
          367
        ],
        [
          811,
          364
        ]
      ]
    },
    {
      "transcription": "Happiness",
      "points": [
        [
          914,
          345
        ],
        [
          1032,
          345
        ],
        [
          1032,
          369
        ],
        [
          914,
          369
        ]
      ]
    },
    {
      "transcription": "GIẤY",
      "points": [
        [
          593,
          476
        ],
        [
          680,
          476
        ],
        [
          680,
          509
        ],
        [
          593,
          509
        ]
      ]
    },
    {
      "transcription": "XÁC",
      "points": [
        [
          691,
          476
        ],
        [
          759,
          476
        ],
        [
          759,
          511
        ],
        [
          691,
          511
        ]
      ]
    },
    {
      "transcription": "NHN",
      "points": [
        [
          770,
          478
        ],
        [
          870,
          478
        ],
        [
          870,
          511
        ],
        [
          770,
          511
        ]
      ]
    },
    {
      "transcription": "NHÂN",
      "points": [
        [
          867,
          476
        ],
        [
          974,
          471
        ],
        [
          976,
          508
        ],
        [
          870,
          514
        ]
      ]
    },
    {
      "transcription": "VIÊN",
      "points": [
        [
          982,
          471
        ],
        [
          1073,
          471
        ],
        [
          1073,
          511
        ],
        [
          982,
          511
        ]
      ]
    },
    {
      "transcription": "CERTIFI",
      "points": [
        [
          564,
          518
        ],
        [
          716,
          518
        ],
        [
          716,
          549
        ],
        [
          564,
          549
        ]
      ]
    },
    {
      "transcription": "CATE",
      "points": [
        [
          709,
          520
        ],
        [
          798,
          520
        ],
        [
          798,
          551
        ],
        [
          709,
          551
        ]
      ]
    },
    {
      "transcription": "OF",
      "points": [
        [
          800,
          518
        ],
        [
          852,
          518
        ],
        [
          852,
          551
        ],
        [
          800,
          551
        ]
      ]
    },
    {
      "transcription": "EMPI",
      "points": [
        [
          859,
          520
        ],
        [
          943,
          520
        ],
        [
          943,
          551
        ],
        [
          859,
          551
        ]
      ]
    },
    {
      "transcription": "LOYMENT",
      "points": [
        [
          936,
          518
        ],
        [
          1102,
          518
        ],
        [
          1102,
          549
        ],
        [
          936,
          549
        ]
      ]
    },
    {
      "transcription": "Côngty:",
      "points": [
        [
          315,
          626
        ],
        [
          423,
          632
        ],
        [
          421,
          672
        ],
        [
          313,
          666
        ]
      ]
    },
    {
      "transcription": "TNHH34BẠCH",
      "points": [
        [
          419,
          629
        ],
        [
          628,
          634
        ],
        [
          627,
          672
        ],
        [
          418,
          667
        ]
      ]
    },
    {
      "transcription": "ĐNG",
      "points": [
        [
          627,
          634
        ],
        [
          711,
          634
        ],
        [
          711,
          667
        ],
        [
          627,
          667
        ]
      ]
    },
    {
      "transcription": "Company:",
      "points": [
        [
          314,
          691
        ],
        [
          448,
          691
        ],
        [
          448,
          729
        ],
        [
          314,
          729
        ]
      ]
    },
    {
      "transcription": "34BACHDANGLL",
      "points": [
        [
          439,
          687
        ],
        [
          678,
          692
        ],
        [
          677,
          729
        ],
        [
          438,
          724
        ]
      ]
    },
    {
      "transcription": "Địa chỉ:32-32B-34-34A",
      "points": [
        [
          320,
          740
        ],
        [
          580,
          740
        ],
        [
          580,
          771
        ],
        [
          320,
          771
        ]
      ]
    },
    {
      "transcription": "nBình,",
      "points": [
        [
          914,
          742
        ],
        [
          982,
          742
        ],
        [
          982,
          774
        ],
        [
          914,
          774
        ]
      ]
    },
    {
      "transcription": "Thành",
      "points": [
        [
          986,
          747
        ],
        [
          1050,
          747
        ],
        [
          1050,
          771
        ],
        [
          986,
          771
        ]
      ]
    },
    {
      "transcription": "phốHồ",
      "points": [
        [
          1052,
          741
        ],
        [
          1135,
          735
        ],
        [
          1137,
          768
        ],
        [
          1054,
          774
        ]
      ]
    },
    {
      "transcription": "ChíMinh,Việt",
      "points": [
        [
          1134,
          738
        ],
        [
          1291,
          738
        ],
        [
          1291,
          776
        ],
        [
          1134,
          776
        ]
      ]
    },
    {
      "transcription": "Nam",
      "points": [
        [
          318,
          789
        ],
        [
          375,
          789
        ],
        [
          375,
          816
        ],
        [
          318,
          816
        ]
      ]
    },
    {
      "transcription": "Address:",
      "points": [
        [
          317,
          837
        ],
        [
          430,
          843
        ],
        [
          428,
          881
        ],
        [
          315,
          875
        ]
      ]
    },
    {
      "transcription": "32-32B-34-34ABạch",
      "points": [
        [
          427,
          847
        ],
        [
          670,
          847
        ],
        [
          670,
          878
        ],
        [
          427,
          878
        ]
      ]
    },
    {
      "transcription": "Dang",
      "points": [
        [
          673,
          844
        ],
        [
          744,
          853
        ],
        [
          740,
          884
        ],
        [
          669,
          875
        ]
      ]
    },
    {
      "transcription": "BinhDistrict,HoChiMinh",
      "points": [
        [
          900,
          847
        ],
        [
          1223,
          847
        ],
        [
          1223,
          878
        ],
        [
          900,
          878
        ]
      ]
    },
    {
      "transcription": "city",
      "points": [
        [
          1222,
          841
        ],
        [
          1284,
          850
        ],
        [
          1278,
          884
        ],
        [
          1216,
          874
        ]
      ]
    },
    {
      "transcription": "Ward2,",
      "points": [
        [
          743,
          851
        ],
        [
          855,
          851
        ],
        [
          855,
          876
        ],
        [
          743,
          876
        ]
      ]
    },
    {
      "transcription": "Tan",
      "points": [
        [
          850,
          854
        ],
        [
          895,
          854
        ],
        [
          895,
          878
        ],
        [
          850,
          878
        ]
      ]
    },
    {
      "transcription": "Vietnam",
      "points": [
        [
          317,
          886
        ],
        [
          423,
          892
        ],
        [
          422,
          925
        ],
        [
          315,
          920
        ]
      ]
    },
    {
      "transcription": "Mã",
      "points": [
        [
          320,
          951
        ],
        [
          364,
          951
        ],
        [
          364,
          980
        ],
        [
          320,
          980
        ]
      ]
    },
    {
      "transcription": "sốthuế",
      "points": [
        [
          361,
          947
        ],
        [
          452,
          947
        ],
        [
          452,
          980
        ],
        [
          361,
          980
        ]
      ]
    },
    {
      "transcription": "0316933242",
      "points": [
        [
          457,
          947
        ],
        [
          605,
          947
        ],
        [
          605,
          985
        ],
        [
          457,
          985
        ]
      ]
    },
    {
      "transcription": "Taxcode:0316933242",
      "points": [
        [
          316,
          1003
        ],
        [
          584,
          1003
        ],
        [
          584,
          1047
        ],
        [
          316,
          1047
        ]
      ]
    },
    {
      "transcription": "Xác",
      "points": [
        [
          320,
          1071
        ],
        [
          368,
          1071
        ],
        [
          368,
          1098
        ],
        [
          320,
          1098
        ]
      ]
    },
    {
      "transcription": "nhncho/Certificatefor",
      "points": [
        [
          361,
          1067
        ],
        [
          664,
          1067
        ],
        [
          664,
          1105
        ],
        [
          361,
          1105
        ]
      ]
    },
    {
      "transcription": "Họtên",
      "points": [
        [
          320,
          1127
        ],
        [
          402,
          1127
        ],
        [
          402,
          1160
        ],
        [
          320,
          1160
        ]
      ]
    },
    {
      "transcription": "NG",
      "points": [
        [
          409,
          1125
        ],
        [
          464,
          1125
        ],
        [
          464,
          1160
        ],
        [
          409,
          1160
        ]
      ]
    },
    {
      "transcription": "YNHOÀI",
      "points": [
        [
          461,
          1120
        ],
        [
          611,
          1120
        ],
        [
          611,
          1160
        ],
        [
          461,
          1160
        ]
      ]
    },
    {
      "transcription": "NGỌC",
      "points": [
        [
          607,
          1127
        ],
        [
          686,
          1127
        ],
        [
          686,
          1158
        ],
        [
          607,
          1158
        ]
      ]
    },
    {
      "transcription": "Fullnam",
      "points": [
        [
          318,
          1187
        ],
        [
          434,
          1187
        ],
        [
          434,
          1218
        ],
        [
          318,
          1218
        ]
      ]
    },
    {
      "transcription": ":NGUYEI",
      "points": [
        [
          436,
          1185
        ],
        [
          555,
          1185
        ],
        [
          555,
          1216
        ],
        [
          436,
          1216
        ]
      ]
    },
    {
      "transcription": "NHOAINGOC",
      "points": [
        [
          543,
          1183
        ],
        [
          725,
          1183
        ],
        [
          725,
          1220
        ],
        [
          543,
          1220
        ]
      ]
    },
    {
      "transcription": "Ngày",
      "points": [
        [
          315,
          1248
        ],
        [
          379,
          1242
        ],
        [
          383,
          1275
        ],
        [
          318,
          1281
        ]
      ]
    },
    {
      "transcription": "tháng",
      "points": [
        [
          382,
          1247
        ],
        [
          461,
          1247
        ],
        [
          461,
          1278
        ],
        [
          382,
          1278
        ]
      ]
    },
    {
      "transcription": "sinh/Date",
      "points": [
        [
          512,
          1242
        ],
        [
          635,
          1247
        ],
        [
          633,
          1281
        ],
        [
          511,
          1276
        ]
      ]
    },
    {
      "transcription": "ofbirth:",
      "points": [
        [
          627,
          1245
        ],
        [
          734,
          1245
        ],
        [
          734,
          1278
        ],
        [
          627,
          1278
        ]
      ]
    },
    {
      "transcription": "01/01/1995",
      "points": [
        [
          734,
          1245
        ],
        [
          859,
          1245
        ],
        [
          859,
          1276
        ],
        [
          734,
          1276
        ]
      ]
    },
    {
      "transcription": "Giới tinh/Sex:",
      "points": [
        [
          875,
          1240
        ],
        [
          1043,
          1240
        ],
        [
          1043,
          1278
        ],
        [
          875,
          1278
        ]
      ]
    },
    {
      "transcription": "Tnăm",
      "points": [
        [
          450,
          1252
        ],
        [
          514,
          1252
        ],
        [
          514,
          1276
        ],
        [
          450,
          1276
        ]
      ]
    },
    {
      "transcription": ":N/Female",
      "points": [
        [
          1030,
          1243
        ],
        [
          1173,
          1243
        ],
        [
          1173,
          1280
        ],
        [
          1030,
          1280
        ]
      ]
    },
    {
      "transcription": "Tạo,",
      "points": [
        [
          639,
          1305
        ],
        [
          698,
          1305
        ],
        [
          698,
          1338
        ],
        [
          639,
          1338
        ]
      ]
    },
    {
      "transcription": "Thành PhốMTho,",
      "points": [
        [
          798,
          1298
        ],
        [
          1007,
          1303
        ],
        [
          1006,
          1341
        ],
        [
          797,
          1336
        ]
      ]
    },
    {
      "transcription": "TiềnGiang",
      "points": [
        [
          1059,
          1297
        ],
        [
          1192,
          1306
        ],
        [
          1189,
          1346
        ],
        [
          1056,
          1337
        ]
      ]
    },
    {
      "transcription": "Địa",
      "points": [
        [
          320,
          1309
        ],
        [
          368,
          1309
        ],
        [
          368,
          1340
        ],
        [
          320,
          1340
        ]
      ]
    },
    {
      "transcription": "chỉthườngtrú",
      "points": [
        [
          355,
          1307
        ],
        [
          541,
          1307
        ],
        [
          541,
          1338
        ],
        [
          355,
          1338
        ]
      ]
    },
    {
      "transcription": "6ABình",
      "points": [
        [
          547,
          1308
        ],
        [
          644,
          1302
        ],
        [
          646,
          1335
        ],
        [
          549,
          1341
        ]
      ]
    },
    {
      "transcription": "TrungAn,",
      "points": [
        [
          693,
          1307
        ],
        [
          807,
          1307
        ],
        [
          807,
          1338
        ],
        [
          693,
          1338
        ]
      ]
    },
    {
      "transcription": "Tinh",
      "points": [
        [
          1009,
          1309
        ],
        [
          1059,
          1309
        ],
        [
          1059,
          1336
        ],
        [
          1009,
          1336
        ]
      ]
    },
    {
      "transcription": "Address:6A",
      "points": [
        [
          457,
          1363
        ],
        [
          598,
          1363
        ],
        [
          598,
          1394
        ],
        [
          457,
          1394
        ]
      ]
    },
    {
      "transcription": "Binh",
      "points": [
        [
          600,
          1363
        ],
        [
          661,
          1363
        ],
        [
          661,
          1396
        ],
        [
          600,
          1396
        ]
      ]
    },
    {
      "transcription": "Tạo,",
      "points": [
        [
          657,
          1365
        ],
        [
          714,
          1365
        ],
        [
          714,
          1398
        ],
        [
          657,
          1398
        ]
      ]
    },
    {
      "transcription": "ThoCity,",
      "points": [
        [
          881,
          1358
        ],
        [
          989,
          1363
        ],
        [
          987,
          1401
        ],
        [
          879,
          1396
        ]
      ]
    },
    {
      "transcription": "Giang",
      "points": [
        [
          1045,
          1362
        ],
        [
          1117,
          1368
        ],
        [
          1114,
          1399
        ],
        [
          1042,
          1393
        ]
      ]
    },
    {
      "transcription": "Province",
      "points": [
        [
          1115,
          1364
        ],
        [
          1226,
          1370
        ],
        [
          1224,
          1401
        ],
        [
          1113,
          1396
        ]
      ]
    },
    {
      "transcription": "BACH",
      "points": [
        [
          1420,
          1356
        ],
        [
          1475,
          1356
        ],
        [
          1475,
          1383
        ],
        [
          1420,
          1383
        ]
      ]
    },
    {
      "transcription": "Permanent",
      "points": [
        [
          318,
          1372
        ],
        [
          450,
          1372
        ],
        [
          450,
          1396
        ],
        [
          318,
          1396
        ]
      ]
    },
    {
      "transcription": "Trung",
      "points": [
        [
          718,
          1367
        ],
        [
          789,
          1367
        ],
        [
          789,
          1398
        ],
        [
          718,
          1398
        ]
      ]
    },
    {
      "transcription": "An,",
      "points": [
        [
          786,
          1367
        ],
        [
          834,
          1367
        ],
        [
          834,
          1398
        ],
        [
          786,
          1398
        ]
      ]
    },
    {
      "transcription": "My",
      "points": [
        [
          832,
          1367
        ],
        [
          880,
          1367
        ],
        [
          880,
          1398
        ],
        [
          832,
          1398
        ]
      ]
    },
    {
      "transcription": "Tien",
      "points": [
        [
          993,
          1367
        ],
        [
          1050,
          1367
        ],
        [
          1050,
          1394
        ],
        [
          993,
          1394
        ]
      ]
    },
    {
      "transcription": "Địachỉhiện",
      "points": [
        [
          316,
          1423
        ],
        [
          455,
          1423
        ],
        [
          455,
          1463
        ],
        [
          316,
          1463
        ]
      ]
    },
    {
      "transcription": "71/48",
      "points": [
        [
          498,
          1425
        ],
        [
          570,
          1425
        ],
        [
          570,
          1456
        ],
        [
          498,
          1456
        ]
      ]
    },
    {
      "transcription": "Đườ",
      "points": [
        [
          573,
          1427
        ],
        [
          632,
          1427
        ],
        [
          632,
          1454
        ],
        [
          573,
          1454
        ]
      ]
    },
    {
      "transcription": "mgĐiệnBiênPhủ,Phường2,",
      "points": [
        [
          622,
          1418
        ],
        [
          945,
          1414
        ],
        [
          946,
          1458
        ],
        [
          623,
          1463
        ]
      ]
    },
    {
      "transcription": "tại:",
      "points": [
        [
          455,
          1429
        ],
        [
          507,
          1429
        ],
        [
          507,
          1456
        ],
        [
          455,
          1456
        ]
      ]
    },
    {
      "transcription": "QunBình",
      "points": [
        [
          943,
          1423
        ],
        [
          1073,
          1423
        ],
        [
          1073,
          1460
        ],
        [
          943,
          1460
        ]
      ]
    },
    {
      "transcription": "Thạnh,",
      "points": [
        [
          1068,
          1425
        ],
        [
          1150,
          1425
        ],
        [
          1150,
          1458
        ],
        [
          1068,
          1458
        ]
      ]
    },
    {
      "transcription": "TP.Hồ ChíMinh",
      "points": [
        [
          1152,
          1423
        ],
        [
          1348,
          1423
        ],
        [
          1348,
          1460
        ],
        [
          1152,
          1460
        ]
      ]
    },
    {
      "transcription": "Temparary",
      "points": [
        [
          316,
          1485
        ],
        [
          448,
          1485
        ],
        [
          448,
          1523
        ],
        [
          316,
          1523
        ]
      ]
    },
    {
      "transcription": "address",
      "points": [
        [
          455,
          1485
        ],
        [
          545,
          1485
        ],
        [
          545,
          1518
        ],
        [
          455,
          1518
        ]
      ]
    },
    {
      "transcription": "71/48Dien",
      "points": [
        [
          556,
          1480
        ],
        [
          682,
          1485
        ],
        [
          681,
          1519
        ],
        [
          554,
          1513
        ]
      ]
    },
    {
      "transcription": "BienPhu",
      "points": [
        [
          682,
          1485
        ],
        [
          789,
          1485
        ],
        [
          789,
          1518
        ],
        [
          682,
          1518
        ]
      ]
    },
    {
      "transcription": "Ward2,",
      "points": [
        [
          805,
          1485
        ],
        [
          889,
          1485
        ],
        [
          889,
          1516
        ],
        [
          805,
          1516
        ]
      ]
    },
    {
      "transcription": ",Bii",
      "points": [
        [
          884,
          1487
        ],
        [
          927,
          1487
        ],
        [
          927,
          1512
        ],
        [
          884,
          1512
        ]
      ]
    },
    {
      "transcription": "nhThanh",
      "points": [
        [
          925,
          1485
        ],
        [
          1025,
          1485
        ],
        [
          1025,
          1516
        ],
        [
          925,
          1516
        ]
      ]
    },
    {
      "transcription": "District,",
      "points": [
        [
          1025,
          1485
        ],
        [
          1125,
          1485
        ],
        [
          1125,
          1516
        ],
        [
          1025,
          1516
        ]
      ]
    },
    {
      "transcription": "HoChiMinhCity",
      "points": [
        [
          1116,
          1483
        ],
        [
          1327,
          1483
        ],
        [
          1327,
          1520
        ],
        [
          1116,
          1520
        ]
      ]
    },
    {
      "transcription": "Bộphn",
      "points": [
        [
          311,
          1543
        ],
        [
          418,
          1543
        ],
        [
          418,
          1583
        ],
        [
          311,
          1583
        ]
      ]
    },
    {
      "transcription": "Kinhdoanh",
      "points": [
        [
          420,
          1540
        ],
        [
          561,
          1540
        ],
        [
          561,
          1578
        ],
        [
          420,
          1578
        ]
      ]
    },
    {
      "transcription": "Chức",
      "points": [
        [
          609,
          1543
        ],
        [
          680,
          1543
        ],
        [
          680,
          1574
        ],
        [
          609,
          1574
        ]
      ]
    },
    {
      "transcription": "cvụ:Chuyênviên",
      "points": [
        [
          668,
          1545
        ],
        [
          866,
          1545
        ],
        [
          866,
          1576
        ],
        [
          668,
          1576
        ]
      ]
    },
    {
      "transcription": "Business",
      "points": [
        [
          473,
          1607
        ],
        [
          573,
          1607
        ],
        [
          573,
          1638
        ],
        [
          473,
          1638
        ]
      ]
    },
    {
      "transcription": "Position:.Specialist",
      "points": [
        [
          600,
          1601
        ],
        [
          834,
          1598
        ],
        [
          834,
          1638
        ],
        [
          600,
          1641
        ]
      ]
    },
    {
      "transcription": "Mứclươnghàng",
      "points": [
        [
          314,
          1667
        ],
        [
          495,
          1667
        ],
        [
          495,
          1698
        ],
        [
          314,
          1698
        ]
      ]
    },
    {
      "transcription": "thánghiệntại/Current",
      "points": [
        [
          498,
          1667
        ],
        [
          755,
          1667
        ],
        [
          755,
          1698
        ],
        [
          498,
          1698
        ]
      ]
    },
    {
      "transcription": "tmonthlyS",
      "points": [
        [
          745,
          1667
        ],
        [
          866,
          1667
        ],
        [
          866,
          1698
        ],
        [
          745,
          1698
        ]
      ]
    },
    {
      "transcription": "salary",
      "points": [
        [
          855,
          1667
        ],
        [
          927,
          1667
        ],
        [
          927,
          1701
        ],
        [
          855,
          1701
        ]
      ]
    }
  ]
}